Hive_ML/__init__.py
Hive_ML/_version.py
Hive_ML/configs/Radiodynamics_12_config.json
Hive_ML/configs/Radiodynamics_config.json
Hive_ML/configs/Radiomics_config.json
Hive_ML/configs/__init__.py
Hive_ML/data_loader/__init__.py
Hive_ML/data_loader/feature_loader.py
Hive_ML/data_loader/image_loader.py
Hive_ML/evaluation/__init__.py
Hive_ML/evaluation/model_evaluation.py
Hive_ML/extraction/__init__.py
Hive_ML/extraction/feature_extraction.py
Hive_ML/feature_generation/__init__.py
Hive_ML/feature_generation/perfusion_features.py
Hive_ML/training/__init__.py
Hive_ML/training/model_trainer.py
Hive_ML/training/models.py
Hive_ML/utilities/__init__.py
Hive_ML/utilities/feature_utils.py
Hive_ML-1.0.1.data/data/requirements.txt
Hive_ML_scripts/Hive_ML_extract_radiomics.py
Hive_ML_scripts/Hive_ML_feature_selection.py
Hive_ML_scripts/Hive_ML_generate_perfusion_maps.py
Hive_ML_scripts/Hive_ML_model_fitting.py
Hive_ML_scripts/__init__.py
Hive_ML-1.0.1.dist-info/METADATA
Hive_ML-1.0.1.dist-info/WHEEL
Hive_ML-1.0.1.dist-info/entry_points.txt
Hive_ML-1.0.1.dist-info/top_level.txt
Hive_ML-1.0.1.dist-info/RECORD
