Metadata-Version: 2.1
Name: Hive-ML
Version: 1.0.1
Summary: Python package to run Machine Learning Experiments, within the Hive Framework.
Home-page: https://github.com/MAIA-KTH/Hive_ML.git
Author: Bendazzoli Simone
Author-email: simben@kth.se
License: GPLv3
Project-URL: Documentation, https://hive-ml.readthedocs.io
Project-URL: Bug Tracker, https://github.com/MAIA-KTH/Hive_ML/issues
Project-URL: Source Code, https://github.com/MAIA-KTH/Hive_ML
Keywords: machine learning,image classification,PCR,medical image analysis,DCE MRI,radiomics,feature selection,radiodynamics
Platform: OS Independent
Classifier: Intended Audience :: Developers
Classifier: Intended Audience :: Education
Classifier: Intended Audience :: Science/Research
Classifier: Intended Audience :: Healthcare Industry
Classifier: Programming Language :: C++
Classifier: Programming Language :: Python :: 3
Classifier: Programming Language :: Python :: 3.8
Classifier: Programming Language :: Python :: 3.9
Classifier: Programming Language :: Python :: 3.10
Classifier: Topic :: Scientific/Engineering
Classifier: Topic :: Scientific/Engineering :: Artificial Intelligence
Classifier: Topic :: Scientific/Engineering :: Medical Science Apps.
Classifier: Topic :: Scientific/Engineering :: Information Analysis
Classifier: Topic :: Software Development
Classifier: Topic :: Software Development :: Libraries
Classifier: Typing :: Typed
Requires-Python: >=3.8
Requires-Dist: numpy (==1.23.5)
Requires-Dist: SimpleITK (==2.2.1)
Requires-Dist: six (==1.16.0)
Requires-Dist: hive-maia (==1.1.2rc2)
Requires-Dist: pandas (==1.5.3)
Requires-Dist: pyradiomics (==3.0.1)
Requires-Dist: tqdm (==4.64.1)
Requires-Dist: mlflow (==2.5.0)
Requires-Dist: pysftp (==0.2.9)
Requires-Dist: mlxtend (==0.22.0)
Requires-Dist: scikit-learn (==1.2.1)
Requires-Dist: scipy (==1.10.0)
Requires-Dist: plotly (==5.9.0)
Requires-Dist: yellowbrick (==1.5)
Requires-Dist: kaleido (==0.2.1)
